{"Id":26512,"Name":"0247R1-mcneilly-red","Description":"Nam aliquam lorem. At faucibus, fusce congue, quibusdam vel. Elementum magna, vel scelerisque nunc.\r\nConubia vivamus, eros felis. Elementum magna, vel scelerisque nunc. Incididunt cras amet, duis sed scelerisque.\r\nConvallis ut. Aliquam morbi vehicula.\r\nLobortis a sem, orci ornare.\r\n","Photos":{"Original":"original\\0247R1-mcneilly-red.jpg","Display":"display\\0247R1-mcneilly-red.jpg","Mobile":"mobile\\0247R1-mcneilly-red.jpg","Thumb":"thumb\\0247R1-mcneilly-red.jpg"},"Price":549.0,"Categories":["Youth","Piers & Bookcases","Youth"]}