{"Id":9787,"Name":"0560C1-0560O1-mcneilly-stat","Description":"Condimentum vel nam.\r\nTellus arcu natoque, sagittis feugiat. Eget mi sem, erat nemo in, sit morbi interdum.\r\nMi sem, velit eget vulputate. Fermentum turpis. Suscipit ultrices tincidunt.\r\n","Photos":{"Original":"original\\0560C1-0560O1-mcneilly-stat.jpg","Display":"display\\0560C1-0560O1-mcneilly-stat.jpg","Mobile":"mobile\\0560C1-0560O1-mcneilly-stat.jpg","Thumb":"thumb\\0560C1-0560O1-mcneilly-stat.jpg"},"Price":699.0,"Categories":["Bedroom","Dressers & Chests","Bedroom"]}