{"Id":19351,"Name":"090800leathersofa","Description":"Dolor sed, sed et consectetuer, facilisi in. Vestibulum in, integer arcu arcu.\r\nMorbi dictum scelerisque, eget facilisi, imperdiet ullamcorper ac.\r\nNec et. Neque a laoreet, ullam bibendum. Adipiscing inceptos, faucibus velit suspendisse, donec quisque purus.\r\n","Photos":{"Original":"original\\090800leathersofa.jpg","Display":"display\\090800leathersofa.jpg","Mobile":"mobile\\090800leathersofa.jpg","Thumb":"thumb\\090800leathersofa.jpg"},"Price":449.0,"Categories":["Entertainment","Patio Table Sets","Entertainment"]}