{"Id":11359,"Name":"1150-210-220GOcaleb-dresser-mirror","Slug":"1150-210-220GOcaleb-dresser-mirror","Description":"Maecenas est, id felis, placerat pellentesque suscipit.\r\nVitae molestie sed. Fusce sit, ac tellus. Lorem a nunc, quis eu, ut et. At nec, a lacinia laoreet.\r\nPorttitor vestibulum eu, dolor magnis phasellus, nihil pretium. Semper nullam duis, venenatis a leo, proin consequat. Maecenas est, id felis, placerat pellentesque suscipit.\r\n","Photos":{"Original":"1150-210-220GOcaleb-dresser-mirror.jpg","Display":"1150-210-220GOcaleb-dresser-mirror.jpg","Mobile":"1150-210-220GOcaleb-dresser-mirror.jpg","Thumb":"1150-210-220GOcaleb-dresser-mirror.jpg"},"Price":649.0,"Categories":["Mattress","Accent/Decor","Mattress"],"Related":[{"Id":11359,"Name":"YLveranda420bench","Slug":"YLveranda420bench","Photos":{"Original":"YLveranda420bench.jpg","Display":"YLveranda420bench.jpg","Mobile":"YLveranda420bench.jpg","Thumb":"YLveranda420bench.jpg"},"Price":299.0},{"Id":11359,"Name":"DAbobmackieclassicscommode2","Slug":"DAbobmackieclassicscommode2","Photos":{"Original":"DAbobmackieclassicscommode2.jpg","Display":"DAbobmackieclassicscommode2.jpg","Mobile":"DAbobmackieclassicscommode2.jpg","Thumb":"DAbobmackieclassicscommode2.jpg"},"Price":649.0},{"Id":11359,"Name":"6120occ-SLF-Madison","Slug":"6120occ-SLF-Madison","Photos":{"Original":"6120occ-SLF-Madison.jpg","Display":"6120occ-SLF-Madison.jpg","Mobile":"6120occ-SLF-Madison.jpg","Thumb":"6120occ-SLF-Madison.jpg"},"Price":299.0}],"Reviews":["Maecenas est, id felis, placerat pellentesque suscipit.\r\nVitae molestie sed. Fusce sit, ac tellus. Lorem a nunc, quis eu, ut et. At nec, a lacinia laoreet.\r\nPorttitor vestibulum eu, dolor magnis phasellus, nihil pretium. Semper nullam duis, venenatis a leo, proin consequat. Maecenas est, id felis, placerat pellentesque suscipit.\r\n"],"AvgRating":1}