{"Id":26193,"Name":"121894bombaychest","Description":"Congue vestibulum tempus. Ullamcorper et etiam.\r\nEt elementum, nulla habitant suspendisse. Rhoncus fringilla amet, at libero, dolor ligula. Non fusce gravida.\r\nCras ullamcorper dictum, leo non.\r\nTorquent pellentesque. Sapien aliquam mollis, quam quisquam sed, tellus id. Ac nonummy amet, mi cras.\r\n","Photos":{"Original":"original\\121894bombaychest.jpg","Display":"display\\121894bombaychest.jpg","Mobile":"mobile\\121894bombaychest.jpg","Thumb":"thumb\\121894bombaychest.jpg"},"Price":199.0,"Categories":["Youth","Dining","Youth"]}