{"Id":5889,"Name":"158-concord","Description":"Sit lorem mauris.\r\nArcu sapiente imperdiet, vitae eu elit. Nullam urna. Sed mauris aliquam, morbi sem senectus. Mollit in condimentum, ut lectus, suspendisse neque tellus. Ut sit, rutrum sociis proin, possimus sodales.\r\nBlandit ligula, a libero duis. Vitae vestibulum, volutpat mus taciti. Sit viverra, curabitur pretium integer, eu ullamcorper pellentesque. Ipsum sapien nonummy, erat nulla at, ullamcorper cum id. Mattis enim, cras ac.\r\n","Photos":{"Original":"original\\158-concord.jpg","Display":"display\\158-concord.jpg","Mobile":"mobile\\158-concord.jpg","Thumb":"thumb\\158-concord.jpg"},"Price":149.0,"Categories":["Dining","Patio Table","Dining"]}