{"Id":24859,"Name":"2272","Description":"Dictum eu. Sit volutpat necessitatibus, suspendisse mauris, convallis mauris sapien. Mauris dui, mi nunc mauris, pede wisi.\r\nCommodo eget, sem tellus id, a sollicitudin eu. Tincidunt pellentesque, scelerisque etiam. Amet porttitor malesuada, non cursus. Vivamus sodales, sodales vel, facilisi non pharetra.\r\nMi magna.\r\n","Photos":{"Original":"original\\2272.jpg","Display":"display\\2272.jpg","Mobile":"mobile\\2272.jpg","Thumb":"thumb\\2272.jpg"},"Price":549.0,"Categories":["Youth","Lounge Seating","Youth"]}