{"Id":36135,"Name":"274-252799-08-03-21B-06","Description":"Nam ac ac, egestas lacus nec, in donec semper. Nec aliquet, nibh tellus pretium. Fermentum dictumst elementum, id hac ante, augue in lorem.\r\nEget purus reiciendis.\r\nDiam pellentesque.\r\nAmet consectetuer mauris, dictum vel congue, hendrerit cras mauris. Praesent lorem a, aptent donec. Per sodales, posuere urna, sollicitudin ut.\r\n","Photos":{"Original":"original\\274-252799-08-03-21B-06.jpg","Display":"display\\274-252799-08-03-21B-06.jpg","Mobile":"mobile\\274-252799-08-03-21B-06.jpg","Thumb":"thumb\\274-252799-08-03-21B-06.jpg"},"Price":749.0,"Categories":["Sectionals","Living Room","Sectionals"]}