{"Id":19946,"Name":"437-Broadway-Sectional-Leather-Saddle","Description":"Elementum vehicula. Eget est eu, euismod vivamus.\r\nLibero lobortis mollis, ac praesent placerat, in malesuada. Velit arcu, vestibulum feugiat faucibus, libero pretium phasellus.\r\nMetus sollicitudin, luctus ullamcorper mauris, vulputate enim. Suscipit urna, purus metus morbi, euismod integer.\r\n","Photos":{"Original":"original\\437-Broadway-Sectional-Leather-Saddle.jpg","Display":"display\\437-Broadway-Sectional-Leather-Saddle.jpg","Mobile":"mobile\\437-Broadway-Sectional-Leather-Saddle.jpg","Thumb":"thumb\\437-Broadway-Sectional-Leather-Saddle.jpg"},"Price":449.0,"Categories":["Entertainment","Cabinets & File Storage","Entertainment"]}