{"Id":43351,"Name":"5000-660680-720730-630600","Description":"Vestibulum nec metus, a suspendisse. Wisi vestibulum imperdiet, volutpat eu. Pellentesque mi, perspiciatis cras amet. Quasi ante natoque. Turpis commodo, quis commodo, et velit maecenas.\r\nDolor sed, sed et consectetuer, facilisi in. Vitae netus et, proin eros in.\r\nMalesuada hendrerit egestas, lorem amet eros, wisi velit ultricies.\r\nViverra tempor, eu a, maecenas lectus. Risus commodo, malesuada montes nunc. Vestibulum wisi pretium, congue aenean.\r\n","Photos":{"Original":"original\\5000-660680-720730-630600.jpg","Display":"display\\5000-660680-720730-630600.jpg","Mobile":"mobile\\5000-660680-720730-630600.jpg","Thumb":"thumb\\5000-660680-720730-630600.jpg"},"Price":949.0,"Categories":["Patio Chairs","Innerspring Mattresses","Patio Chairs"]}