{"Id":27320,"Name":"640-273-blanket-EngCOUNTRY","Description":"Libero metus, sapien vitae odio. Vestibulum in, integer arcu arcu. Tortor libero libero, cras pellentesque, sagittis quam leo.\r\nA congue amet, neque tempus, accumsan elit conubia.\r\nEget etiam.\r\nPlatea lectus, interdum urna proin, habitasse lobortis. Duis faucibus, molestie ante adipiscing, id eget elit. Tempor nulla libero, est vivamus, turpis non. Libero tempor lobortis, nec sed dui.\r\n","Photos":{"Original":"original\\640-273-blanket-EngCOUNTRY.jpg","Display":"display\\640-273-blanket-EngCOUNTRY.jpg","Mobile":"mobile\\640-273-blanket-EngCOUNTRY.jpg","Thumb":"thumb\\640-273-blanket-EngCOUNTRY.jpg"},"Price":599.0,"Categories":["Patio","Lounge Seating","Patio"]}