{"Id":42175,"Name":"653-014-openStor-CIRCUS","Description":"Diam integer id, ut vel dictum. Parturient urna. Tristique urna ultricies. In neque phasellus, amet quis.\r\nSuspendisse nulla, pulvinar facilisi, a at. Molestie sit at, tristique ligula, tellus neque.\r\nEt dictum, proin gravida, elit sit cum.\r\nIaculis et. Mauris ipsum, eget vitae. Eros at. Viverra nam rutrum, velit dictum.\r\n","Photos":{"Original":"original\\653-014-openStor-CIRCUS.jpg","Display":"display\\653-014-openStor-CIRCUS.jpg","Mobile":"mobile\\653-014-openStor-CIRCUS.jpg","Thumb":"thumb\\653-014-openStor-CIRCUS.jpg"},"Price":849.0,"Categories":["TV Consoles","Accent/Decor","TV Consoles"]}