{"Id":11613,"Name":"70-stevesilver-sean","Description":"Omnis vulputate, sed sed lobortis, duis integer. Ante vivamus, mauris morbi dictum, nulla ipsum.\r\nLorem ut nulla, orci at. Suscipit ultrices tincidunt. Dolor fames tellus. Ac in tortor, quisque lectus, cubilia non bibendum.\r\nIncididunt cras amet, duis sed scelerisque.\r\n","Photos":{"Original":"original\\70-stevesilver-sean.jpg","Display":"display\\70-stevesilver-sean.jpg","Mobile":"mobile\\70-stevesilver-sean.jpg","Thumb":"thumb\\70-stevesilver-sean.jpg"},"Price":999.0,"Categories":["Mattress","Media Chests","Mattress"]}