{"Id":20001,"Name":"77252-palliser-twyla","Description":"Et vehicula, interdum ac vestibulum, lorem vulputate. A arcu magna, praesent duis.\r\nLorem etiam quam. Pharetra nec posuere, diam morbi est, suscipit hendrerit.\r\nUt aliquam, neque purus, sit massa nullam. Quis in, per libero id.\r\n","Photos":{"Original":"original\\77252-palliser-twyla.jpg","Display":"display\\77252-palliser-twyla.jpg","Mobile":"mobile\\77252-palliser-twyla.jpg","Thumb":"thumb\\77252-palliser-twyla.jpg"},"Price":449.0,"Categories":["Entertainment","Youth - Dressers & Chests","Entertainment"]}