{"Id":7711,"Name":"774-668-PARSONS","Description":"Justo sit et, placerat nisl.\r\nDictum sed nascetur, sapien pellentesque, imperdiet vestibulum tincidunt. Venenatis consequat faucibus, lorem varius, in urna vivamus.\r\nMetus sollicitudin, luctus ullamcorper mauris, vulputate enim.\r\n","Photos":{"Original":"original\\774-668-PARSONS.jpg","Display":"display\\774-668-PARSONS.jpg","Mobile":"mobile\\774-668-PARSONS.jpg","Thumb":"thumb\\774-668-PARSONS.jpg"},"Price":199.0,"Categories":["Bedroom","Innerspring Mattresses","Bedroom"]}