{"Id":44420,"Name":"781-11terracegardeniiCH","Description":"Felis et, bibendum vel eu, lacinia amet ligula. Fringilla praesent, consectetuer id. Elit blandit cursus, ad nullam. Amet quis nec, eu diam, etiam mauris morbi.\r\nSed ut. Amet porttitor malesuada, non cursus.\r\nSuspendisse aenean. Nec non.\r\nFringilla condimentum, eu ante gravida, dignissim imperdiet pulvinar.\r\n","Photos":{"Original":"original\\781-11terracegardeniiCH.jpg","Display":"display\\781-11terracegardeniiCH.jpg","Mobile":"mobile\\781-11terracegardeniiCH.jpg","Thumb":"thumb\\781-11terracegardeniiCH.jpg"},"Price":649.0,"Categories":["Piers & Bookcases","Patio","Piers & Bookcases"]}