{"Id":7553,"Name":"8701-79,-93,-92-European-Elements","Description":"Ut pellentesque.\r\nIpsum pellentesque lectus.\r\nLibero metus, sapien vitae odio. Interdum mi eget. Vulputate cursus libero.\r\n","Photos":{"Original":"original\\8701-79,-93,-92-European-Elements.jpg","Display":"display\\8701-79,-93,-92-European-Elements.jpg","Mobile":"mobile\\8701-79,-93,-92-European-Elements.jpg","Thumb":"thumb\\8701-79,-93,-92-European-Elements.jpg"},"Price":199.0,"Categories":["Bedroom","Youth","Bedroom"]}