{"Id":46988,"Name":"8701-60,-58,-59,-54-European-Elements","Description":"Et sed mauris, eu ultrices arcu, ipsum risus. Non ac rutrum. Dictum nibh. Amet wisi, quis fusce, a dictum.\r\nUrna aliquet et. In tempor. Sed mauris aliquam, morbi sem senectus. Erat tellus posuere.\r\nDolor fames tellus. Parturient urna. Mollit in condimentum, ut lectus, suspendisse neque tellus.\r\nMauris neque, in sed, cursus tempor.\r\n","Photos":{"Original":"original\\8701-60,-58,-59,-54-European-Elements.jpg","Display":"display\\8701-60,-58,-59,-54-European-Elements.jpg","Mobile":"mobile\\8701-60,-58,-59,-54-European-Elements.jpg","Thumb":"thumb\\8701-60,-58,-59,-54-European-Elements.jpg"},"Price":949.0,"Categories":["Hybrid Mattresses","Entertainment","Hybrid Mattresses"]}