{"Id":5844,"Name":"884-220-demilune-BACHELOR","Description":"Purus velit, fringilla aenean.\r\nVivamus ac. Sed wisi consectetuer, urna natoque justo. Porttitor aenean. Lobortis urna quisque, phasellus vel.\r\nVitae wisi, vestibulum sodales. Dolor fames tellus.\r\n","Photos":{"Original":"original\\884-220-demilune-BACHELOR.jpg","Display":"display\\884-220-demilune-BACHELOR.jpg","Mobile":"mobile\\884-220-demilune-BACHELOR.jpg","Thumb":"thumb\\884-220-demilune-BACHELOR.jpg"},"Price":649.0,"Categories":["Dining","Patio","Dining"]}