{"Id":23958,"Name":"9330-930GOartist-basin","Description":"Odio malesuada lacinia, cras vestibulum, libero duis eleifend. Erat ratione sit, ac integer. Potenti pretium, ac quam.\r\nTortor eu vestibulum, enim lacus. Quasi egestas, et enim velit. Donec vestibulum, mauris placerat duis, erat molestie in.\r\nNibh metus, lacus vestibulum, nisl amet nec. In sed risus, urna egestas tincidunt, ut eget odit. Sagittis mauris et, sit porta.\r\n","Photos":{"Original":"original\\9330-930GOartist-basin.jpg","Display":"display\\9330-930GOartist-basin.jpg","Mobile":"mobile\\9330-930GOartist-basin.jpg","Thumb":"thumb\\9330-930GOartist-basin.jpg"},"Price":499.0,"Categories":["Youth","Dining & Table Sets","Youth"]}