{"Id":2104,"Name":"935-264-mag-GARDENdist","Description":"Sit viverra augue, venenatis wisi neque, ultricies luctus.\r\nLacus aliquam felis, pellentesque metus, nec fringilla eleifend.\r\nNec aliquam nunc. Pede vitae, ultrices eu dictum. Venenatis consequat faucibus, lorem varius, in urna vivamus. Suscipit vivamus rutrum, sed et donec.\r\n","Photos":{"Original":"original\\935-264-mag-GARDENdist.jpg","Display":"display\\935-264-mag-GARDENdist.jpg","Mobile":"mobile\\935-264-mag-GARDENdist.jpg","Thumb":"thumb\\935-264-mag-GARDENdist.jpg"},"Price":70.0,"Categories":["Living Room","Loveseats","Living Room"]}