{"Id":7395,"Name":"962-069-257-loft-R-ONTARIO","Description":"Viverra porttitor, morbi saepe.\r\nAliquip ligula sed, accumsan gravida. Nec scelerisque, eget vitae praesent. Amet scelerisque, aenean arcu at.\r\nMi pede blandit, elit nullam nibh, arcu dapibus ut. Lectus orci, fames velit. Vitae molestie sed.\r\n","Photos":{"Original":"original\\962-069-257-loft-R-ONTARIO.jpg","Display":"display\\962-069-257-loft-R-ONTARIO.jpg","Mobile":"mobile\\962-069-257-loft-R-ONTARIO.jpg","Thumb":"thumb\\962-069-257-loft-R-ONTARIO.jpg"},"Price":399.0,"Categories":["Dining","Entertainment","Dining"]}