{"Id":40364,"Name":"artisan-oak-cocktail-table","Description":"Vitae molestie sed. Non maecenas consequat, pede dictum sit, rutrum diam vitae. Nec et. Class a, et libero, mollis felis.\r\nSem ipsum ac, tortor augue lobortis, viverra id.\r\nLaborum libero, turpis in, nullam arcu lobortis. Sed mauris aliquam, morbi sem senectus. Dolor fames tellus.\r\nLorem etiam quam. Et elementum, nulla habitant suspendisse. Tellus eleifend, ut semper, pellentesque diam.\r\n","Photos":{"Original":"original\\artisan-oak-cocktail-table.jpg","Display":"display\\artisan-oak-cocktail-table.jpg","Mobile":"mobile\\artisan-oak-cocktail-table.jpg","Thumb":"thumb\\artisan-oak-cocktail-table.jpg"},"Price":849.0,"Categories":["Foam Mattresses","Entertainment","Foam Mattresses"]}