{"Id":8907,"Name":"AT1210S","Slug":"AT1210S","Description":"Dolor dolor, quis erat.\r\nVitae praesent massa, semper nec volutpat. Mauris fusce non, donec urna pellentesque.\r\nTincidunt pellentesque, scelerisque etiam.\r\n","Photos":{"Original":"AT1210S.jpg","Display":"AT1210S.jpg","Mobile":"AT1210S.jpg","Thumb":"AT1210S.jpg"},"Price":199.0,"Categories":["Bedroom","Dining","Bedroom"],"Related":[{"Id":8907,"Name":"4310-CMI-PAR","Slug":"4310-CMI-PAR","Photos":{"Original":"4310-CMI-PAR.jpg","Display":"4310-CMI-PAR.jpg","Mobile":"4310-CMI-PAR.jpg","Thumb":"4310-CMI-PAR.jpg"},"Price":249.0},{"Id":8907,"Name":"3316-&-3216-primo-gestin","Slug":"3316-&-3216-primo-gestin","Photos":{"Original":"3316-&-3216-primo-gestin.jpg","Display":"3316-&-3216-primo-gestin.jpg","Mobile":"3316-&-3216-primo-gestin.jpg","Thumb":"3316-&-3216-primo-gestin.jpg"},"Price":199.0},{"Id":8907,"Name":"DSnottingham13600glassdining","Slug":"DSnottingham13600glassdining","Photos":{"Original":"DSnottingham13600glassdining.jpg","Display":"DSnottingham13600glassdining.jpg","Mobile":"DSnottingham13600glassdining.jpg","Thumb":"DSnottingham13600glassdining.jpg"},"Price":249.0}],"Reviews":["Dolor dolor, quis erat.\r\nVitae praesent massa, semper nec volutpat. Mauris fusce non, donec urna pellentesque.\r\nTincidunt pellentesque, scelerisque etiam.\r\n"],"AvgRating":0}