{"Id":26365,"Name":"Babalu","Description":"Mollis nulla id. Consectetuer elit duis, ipsum lacinia luctus. Purus risus.\r\nPellentesque varius diam. Magna nec aliquip, felis a dis, quis nulla. Semper nullam duis, venenatis a leo, proin consequat.\r\nTurpis ultricies purus, adipiscing dui facilisis, natoque sed.\r\nPorttitor vestibulum eu, dolor magnis phasellus, nihil pretium. Litora quis dui, integer vestibulum facilisi, nunc varius. Egestas mollis. Justo dictumst non, aenean suspendisse pede, enim justo ipsum.\r\n","Photos":{"Original":"original\\Babalu.jpg","Display":"display\\Babalu.jpg","Mobile":"mobile\\Babalu.jpg","Thumb":"thumb\\Babalu.jpg"},"Price":449.0,"Categories":["Youth","Entertainment","Youth"]}