{"Id":7037,"Name":"Bordeaux-","Slug":"Bordeaux-","Description":"Potenti in mauris, elit odio.\r\nLeo feugiat, fusce amet facilisis. Tincidunt vestibulum feugiat, neque pellentesque, vitae scelerisque. Dapibus ut phasellus.\r\nNibh aliquam, facilisis nunc et, vestibulum nam. Ante malesuada atque, donec eget. Nibh quisque, pellentesque malesuada in, wisi eget. Quis amet quam, et et placeat. Vehicula vitae eget.\r\n","Photos":{"Original":"Bordeaux-.jpg","Display":"Bordeaux-.jpg","Mobile":"Bordeaux-.jpg","Thumb":"Bordeaux-.jpg"},"Price":749.0,"Categories":["Dining","Office Chairs","Dining"],"Related":[{"Id":7037,"Name":"DYmidlands7661-63-557writingdesk","Slug":"DYmidlands7661-63-557writingdesk","Photos":{"Original":"DYmidlands7661-63-557writingdesk.jpg","Display":"DYmidlands7661-63-557writingdesk.jpg","Mobile":"DYmidlands7661-63-557writingdesk.jpg","Thumb":"DYmidlands7661-63-557writingdesk.jpg"},"Price":199.0},{"Id":7037,"Name":"f83","Slug":"f83","Photos":{"Original":"f83.jpg","Display":"f83.jpg","Mobile":"f83.jpg","Thumb":"f83.jpg"},"Price":749.0},{"Id":7037,"Name":"3127-Adagio-Sm","Slug":"3127-Adagio-Sm","Photos":{"Original":"3127-Adagio-Sm.jpg","Display":"3127-Adagio-Sm.jpg","Mobile":"3127-Adagio-Sm.jpg","Thumb":"3127-Adagio-Sm.jpg"},"Price":199.0}],"Reviews":[],"AvgRating":0}