{"Id":41914,"Name":"Brentwood-242-","Description":"Curabitur laoreet, rutrum sed, ut lacus lorem. Amet euismod vitae. Dignissim at.\r\nDolor mattis praesent, nam fringilla est, est aenean. Litora sit mi, dolor nec quis. Vestibulum donec et, sollicitudin mi, euismod eleifend.\r\nEuismod auctor massa, dictum hymenaeos suscipit.\r\nPer leo, nulla tortor porta, interdum odio. Viverra in, commodo donec.\r\n","Photos":{"Original":"original\\Brentwood-242-.jpg","Display":"display\\Brentwood-242-.jpg","Mobile":"mobile\\Brentwood-242-.jpg","Thumb":"thumb\\Brentwood-242-.jpg"},"Price":849.0,"Categories":["Dining & Table Sets","Mattress","Dining & Table Sets"]}