{"Id":43303,"Name":"china-buffet","Description":"Mauris neque, in sed, cursus tempor. Libero lobortis mollis, ac praesent placerat, in malesuada. Voluptas turpis. Vitae metus, elit urna ac, vestibulum vel.\r\nCursus faucibus pretium. Cursus mi. Mi a, taciti dui justo.\r\nMauris est. Et pede, a phasellus, vitae libero.\r\nIpsum elit ultrices, magna pretium.\r\n","Photos":{"Original":"original\\china-buffet.jpg","Display":"display\\china-buffet.jpg","Mobile":"mobile\\china-buffet.jpg","Thumb":"thumb\\china-buffet.jpg"},"Price":549.0,"Categories":["Bookshelves","Youth","Bookshelves"]}