{"Id":38868,"Name":"CMLedoWAKULLA","Description":"Vivamus lectus. Vel pellentesque, leo et felis, lacinia mauris. Id nec. Tincidunt ligula vitae, velit adipiscing nonummy, et elit.\r\nDiam pellentesque. Iaculis et.\r\nQuis vestibulum, consectetuer nonummy, donec sed massa. Non neque. Gravida imperdiet cras, erat amet, eget justo. Tortor mauris, metus eu, purus tristique.\r\nMauris dui, mi nunc mauris, pede wisi. Turpis commodo, sapien vitae odio. Mauris lacus a. Mollit in condimentum, ut lectus, suspendisse neque tellus.\r\n","Photos":{"Original":"original\\CMLedoWAKULLA.jpg","Display":"display\\CMLedoWAKULLA.jpg","Mobile":"mobile\\CMLedoWAKULLA.jpg","Thumb":"thumb\\CMLedoWAKULLA.jpg"},"Price":599.0,"Categories":["Piers & Bookcases","Patio","Piers & Bookcases"]}