{"Id":47260,"Name":"DAjessicamcclintockhomearmoireopen3","Description":"In nunc, est duis, eget gravida quam. Rutrum at urna, arcu vestibulum. Aliquam tempus. Ut platea, nec sed, suscipit tincidunt. Curabitur laoreet, rutrum sed, ut lacus lorem.\r\nQuam eget, aliquam non ac, consequat vel interdum. Eu quia in, facilisis velit volutpat. Nunc tincidunt duis, sit eget. Justo dictumst non, aenean suspendisse pede, enim justo ipsum. Omnis vulputate, sed sed lobortis, duis integer.\r\nQuam et proin, vestibulum tincidunt nec. Sodales nec suspendisse.\r\nScelerisque eu. Suspendisse nulla, pulvinar facilisi, a at. Mauris lacus a. Nec varius interdum.\r\n","Photos":{"Original":"original\\DAjessicamcclintockhomearmoireopen3.jpg","Display":"display\\DAjessicamcclintockhomearmoireopen3.jpg","Mobile":"mobile\\DAjessicamcclintockhomearmoireopen3.jpg","Thumb":"thumb\\DAjessicamcclintockhomearmoireopen3.jpg"},"Price":949.0,"Categories":["TV Consoles","Stools","TV Consoles"]}