{"Id":24993,"Name":"DAjessicamcclintockcuriochina","Slug":"DAjessicamcclintockcuriochina","Description":"Pellentesque pulvinar, sit sed. Varius ac. Sit turpis amet, lacus et.\r\nQuam laoreet cras.\r\nVehicula vitae eget.\r\n","Photos":{"Original":"DAjessicamcclintockcuriochina.jpg","Display":"DAjessicamcclintockcuriochina.jpg","Mobile":"DAjessicamcclintockcuriochina.jpg","Thumb":"DAjessicamcclintockcuriochina.jpg"},"Price":999.0,"Categories":["Youth","Bedding & Linen","Youth"],"Related":[{"Id":24993,"Name":"BEDYBElegance120-21","Slug":"BEDYBElegance120-21","Photos":{"Original":"BEDYBElegance120-21.jpg","Display":"BEDYBElegance120-21.jpg","Mobile":"BEDYBElegance120-21.jpg","Thumb":"BEDYBElegance120-21.jpg"},"Price":549.0},{"Id":24993,"Name":"Sawyer","Slug":"Sawyer","Photos":{"Original":"Sawyer.jpg","Display":"Sawyer.jpg","Mobile":"Sawyer.jpg","Thumb":"Sawyer.jpg"},"Price":999.0},{"Id":24993,"Name":"DSmanhattan30700chest","Slug":"DSmanhattan30700chest","Photos":{"Original":"DSmanhattan30700chest.jpg","Display":"DSmanhattan30700chest.jpg","Mobile":"DSmanhattan30700chest.jpg","Thumb":"DSmanhattan30700chest.jpg"},"Price":549.0}],"Reviews":["Pellentesque pulvinar, sit sed. Varius ac. Sit turpis amet, lacus et.\r\nQuam laoreet cras.\r\nVehicula vitae eget.\r\n","Pellentesque pulvinar, sit sed. Varius ac. Sit turpis amet, lacus et.\r\nQuam laoreet cras.\r\nVehicula vitae eget.\r\n","Pellentesque pulvinar, sit sed. Varius ac. Sit turpis amet, lacus et.\r\nQuam laoreet cras.\r\nVehicula vitae eget.\r\n"],"AvgRating":2}