{"Id":27970,"Name":"dakotal-road-panel-bedroom","Description":"Maecenas bibendum erat, nisl urna fermentum, nulla ac turpis. A arcu magna, praesent duis.\r\nPer sodales, posuere urna, sollicitudin ut. Quis vestibulum, consectetuer nonummy, donec sed massa. Massa pretium.\r\nDiam integer id, ut vel dictum.\r\nDonec vestibulum, mauris placerat duis, erat molestie in. Urna leo class, in lectus, arcu nec tortor.\r\n","Photos":{"Original":"original\\dakotal-road-panel-bedroom.jpg","Display":"display\\dakotal-road-panel-bedroom.jpg","Mobile":"mobile\\dakotal-road-panel-bedroom.jpg","Thumb":"thumb\\dakotal-road-panel-bedroom.jpg"},"Price":89.0,"Categories":["Patio","Living Room","Patio"]}