{"Id":1430,"Name":"DAtansublackarmoire","Slug":"DAtansublackarmoire","Description":"Ullamcorper urna.\r\nTellus pellentesque, fusce nec augue, diam in sit.\r\nLuctus cursus, id eu at, dui est. Et dui cum, fusce ultricies lectus, eget ligula fringilla. Libero quam, sit fusce at.\r\n","Photos":{"Original":"DAtansublackarmoire.jpg","Display":"DAtansublackarmoire.jpg","Mobile":"DAtansublackarmoire.jpg","Thumb":"DAtansublackarmoire.jpg"},"Price":799.0,"Categories":["Living Room","Stools","Living Room"],"Related":[{"Id":1430,"Name":"mag","Slug":"mag","Photos":{"Original":"mag.jpg","Display":"mag.jpg","Mobile":"mag.jpg","Thumb":"mag.jpg"},"Price":59.0},{"Id":1430,"Name":"0590S1-0590c1-0590O1-mcneilly-stat","Slug":"0590S1-0590c1-0590O1-mcneilly-stat","Photos":{"Original":"0590S1-0590c1-0590O1-mcneilly-stat.jpg","Display":"0590S1-0590c1-0590O1-mcneilly-stat.jpg","Mobile":"0590S1-0590c1-0590O1-mcneilly-stat.jpg","Thumb":"0590S1-0590c1-0590O1-mcneilly-stat.jpg"},"Price":799.0},{"Id":1430,"Name":"RI-promodesks-218-RTD","Slug":"RI-promodesks-218-RTD","Photos":{"Original":"RI-promodesks-218-RTD.jpg","Display":"RI-promodesks-218-RTD.jpg","Mobile":"RI-promodesks-218-RTD.jpg","Thumb":"RI-promodesks-218-RTD.jpg"},"Price":59.0}],"Reviews":[],"AvgRating":0}