{"Id":3995,"Name":"demilune-BACHELOR-2","Slug":"demilune-BACHELOR-2","Description":"Id sit placerat, faucibus nascetur, a eu.\r\nErat tellus posuere.\r\nSagittis vestibulum, aliquam venenatis massa, aliquam donec posuere.\r\n","Photos":{"Original":"demilune-BACHELOR-2.jpg","Display":"demilune-BACHELOR-2.jpg","Mobile":"demilune-BACHELOR-2.jpg","Thumb":"demilune-BACHELOR-2.jpg"},"Price":399.0,"Categories":["Living Room","Entertainment","Living Room"],"Related":[{"Id":3995,"Name":"121359","Slug":"121359","Photos":{"Original":"121359.jpg","Display":"121359.jpg","Mobile":"121359.jpg","Thumb":"121359.jpg"},"Price":149.0},{"Id":3995,"Name":"whitehaven-vanity-+-stool-2","Slug":"whitehaven-vanity-+-stool-2","Photos":{"Original":"whitehaven-vanity-+-stool-2.jpg","Display":"whitehaven-vanity-+-stool-2.jpg","Mobile":"whitehaven-vanity-+-stool-2.jpg","Thumb":"whitehaven-vanity-+-stool-2.jpg"},"Price":399.0},{"Id":3995,"Name":"16","Slug":"16","Photos":{"Original":"16.jpg","Display":"16.jpg","Mobile":"16.jpg","Thumb":"16.jpg"},"Price":149.0}],"Reviews":[],"AvgRating":0}