{"Id":4851,"Name":"DRnantucket716blcktblwoodladder","Slug":"DRnantucket716blcktblwoodladder","Description":"Vitae ac, hymenaeos lacus nec.\r\nIaculis in est, aptent a sit, pellentesque dictum pharetra. Vel congue a, habitasse tellus. In turpis vitae, tortor maecenas dolor, vitae elementum consectetuer. Amet consectetuer mauris, dictum vel congue, hendrerit cras mauris. At porta, duis lectus, libero facilisis.\r\nLobortis a sem, orci ornare.\r\n","Photos":{"Original":"DRnantucket716blcktblwoodladder.jpg","Display":"DRnantucket716blcktblwoodladder.jpg","Mobile":"DRnantucket716blcktblwoodladder.jpg","Thumb":"DRnantucket716blcktblwoodladder.jpg"},"Price":999.0,"Categories":["Dining","Youth - Bedroom Set","Dining"],"Related":[{"Id":4851,"Name":"2101-12-&-2101-27-&-2101-28-&-2101-10-CN","Slug":"2101-12-&-2101-27-&-2101-28-&-2101-10-CN","Photos":{"Original":"2101-12-&-2101-27-&-2101-28-&-2101-10-CN.jpg","Display":"2101-12-&-2101-27-&-2101-28-&-2101-10-CN.jpg","Mobile":"2101-12-&-2101-27-&-2101-28-&-2101-10-CN.jpg","Thumb":"2101-12-&-2101-27-&-2101-28-&-2101-10-CN.jpg"},"Price":149.0},{"Id":4851,"Name":"victdtable","Slug":"victdtable","Photos":{"Original":"victdtable.jpg","Display":"victdtable.jpg","Mobile":"victdtable.jpg","Thumb":"victdtable.jpg"},"Price":999.0},{"Id":4851,"Name":"Sire","Slug":"Sire","Photos":{"Original":"Sire.jpg","Display":"Sire.jpg","Mobile":"Sire.jpg","Thumb":"Sire.jpg"},"Price":149.0}],"Reviews":[],"AvgRating":0}