{"Id":47958,"Name":"DSbayheights89650canopybedroom","Description":"Congue vestibulum tempus. Ipsum pellentesque lectus. Nunc commodo, dui tristique.\r\nAc aliquet, phasellus sed. Nam nec convallis, sodales ornare ipsum, id blandit.\r\nLectus massa justo. In turpis vitae, tortor maecenas dolor, vitae elementum consectetuer.\r\nEt mollis. Et vehicula, interdum ac vestibulum, lorem vulputate. Lectus dolor, tortor ut dui, semper dignissim vel.\r\n","Photos":{"Original":"original\\DSbayheights89650canopybedroom.jpg","Display":"display\\DSbayheights89650canopybedroom.jpg","Mobile":"mobile\\DSbayheights89650canopybedroom.jpg","Thumb":"thumb\\DSbayheights89650canopybedroom.jpg"},"Price":999.0,"Categories":["Stools","Dining","Stools"]}