{"Id":22043,"Name":"ET1218B","Description":"Eu eget dignissim, lorem wisi suscipit, fusce nec suscipit. Consequat aliquam dolor.\r\nNam ac ac, egestas lacus nec, in donec semper.\r\nPorttitor ultrices eleifend. Tincidunt ligula vitae, velit adipiscing nonummy, et elit. Vestibulum neque diam, ut at ultrices, in sodales id.\r\n","Photos":{"Original":"original\\ET1218B.jpg","Display":"display\\ET1218B.jpg","Mobile":"mobile\\ET1218B.jpg","Thumb":"thumb\\ET1218B.jpg"},"Price":499.0,"Categories":["Entertainment","Youth","Entertainment"]}