{"Id":4548,"Name":"ET3809","Slug":"ET3809","Description":"Mi donec in.\r\nErat ratione sit, ac integer.\r\nLobortis a sem, orci ornare. Turpis velit, elit porttitor vel.\r\n","Photos":{"Original":"ET3809.jpg","Display":"ET3809.jpg","Mobile":"ET3809.jpg","Thumb":"ET3809.jpg"},"Price":199.0,"Categories":["Dining","Bedroom","Dining"],"Related":[{"Id":4548,"Name":"4659-Cloud-Nine-Burg","Slug":"4659-Cloud-Nine-Burg","Description":"Mi donec in.\r\nErat ratione sit, ac integer.\r\nLobortis a sem, orci ornare. Turpis velit, elit porttitor vel.\r\n","Photos":{"Original":"4659-Cloud-Nine-Burg.jpg","Display":"4659-Cloud-Nine-Burg.jpg","Mobile":"4659-Cloud-Nine-Burg.jpg","Thumb":"4659-Cloud-Nine-Burg.jpg"},"Price":149.0,"Categories":["Dining","Bedroom","Dining"],"Related":[]},{"Id":4548,"Name":"199721","Slug":"199721","Description":"Mi donec in.\r\nErat ratione sit, ac integer.\r\nLobortis a sem, orci ornare. Turpis velit, elit porttitor vel.\r\n","Photos":{"Original":"199721.jpg","Display":"199721.jpg","Mobile":"199721.jpg","Thumb":"199721.jpg"},"Price":199.0,"Categories":["Dining","Bedroom","Dining"],"Related":[]},{"Id":4548,"Name":"317830-33siblingrivalry","Slug":"317830-33siblingrivalry","Description":"Mi donec in.\r\nErat ratione sit, ac integer.\r\nLobortis a sem, orci ornare. Turpis velit, elit porttitor vel.\r\n","Photos":{"Original":"317830-33siblingrivalry.jpg","Display":"317830-33siblingrivalry.jpg","Mobile":"317830-33siblingrivalry.jpg","Thumb":"317830-33siblingrivalry.jpg"},"Price":149.0,"Categories":["Dining","Bedroom","Dining"],"Related":[]}]}