{"Id":13868,"Name":"frenchgardenleg.JPG","Description":"Vel erat viverra. Donec interdum scelerisque, hendrerit vestibulum felis, enim aperiam.\r\nA sed. Leo integer, wisi dictum eu. Venenatis consequat faucibus, lorem varius, in urna vivamus. Praesent sed sollicitudin, congue hac. Elit nulla, hendrerit vitae.\r\nMollit in condimentum, ut lectus, suspendisse neque tellus. Proin ultricies vehicula, scelerisque sollicitudin. Vehicula quam adipiscing, id magna amet.\r\n","Photos":{"Original":"original\\frenchgardenleg.JPG","Display":"display\\frenchgardenleg.JPG","Mobile":"mobile\\frenchgardenleg.JPG","Thumb":"thumb\\frenchgardenleg.JPG"},"Price":749.0,"Categories":["Mattress","Bedding & Linen","Mattress"]}