{"Id":20710,"Name":"grandmasatticclosedarmoire","Description":"Aliquam at. Sit fermentum nec.\r\nSociis eu. Vel feugiat sed. Commodo eget, sem tellus id, a sollicitudin eu.\r\nTellus vestibulum lacus, lobortis in, vel pede. Egestas faucibus lorem.\r\n","Photos":{"Original":"original\\grandmasatticclosedarmoire.jpg","Display":"display\\grandmasatticclosedarmoire.jpg","Mobile":"mobile\\grandmasatticclosedarmoire.jpg","Thumb":"thumb\\grandmasatticclosedarmoire.jpg"},"Price":449.0,"Categories":["Entertainment","Living Room","Entertainment"]}