{"Id":15793,"Name":"Jungle-wood-panel-bedroom","Description":"Lorem ipsum dolor sit amet, ornare neque vehicula, sapien donec nunc, nisl sagittis.\r\nNec et. Ut pellentesque. Mi nonummy, euismod ut, ac diam.\r\nPraesent sed sollicitudin, congue hac. Malesuada congue, nec aliquam, elit ultrices inceptos.\r\n","Photos":{"Original":"original\\Jungle-wood-panel-bedroom.jpg","Display":"display\\Jungle-wood-panel-bedroom.jpg","Mobile":"mobile\\Jungle-wood-panel-bedroom.jpg","Thumb":"thumb\\Jungle-wood-panel-bedroom.jpg"},"Price":349.0,"Categories":["Office","Living Room","Office"]}