{"Id":31666,"Name":"KJ4091occasionals","Description":"Sed auctor. Cum ante nec, sed libero amet, elementum felis metus. Magna nec aliquip, felis a dis, quis nulla. Cubilia donec vel, semper vehicula.\r\nIpsum elit ultrices, magna pretium. Tincidunt ac. Porta interdum, arcu phasellus.\r\nJusto sit et, placerat nisl. A sed. Justo sit et, placerat nisl.\r\nMaecenas in, nibh elit id, condimentum dolor. Mauris dui, mi nunc mauris, pede wisi. Nulla sed. Est cras, et ante nulla, scelerisque nascetur wisi. Laborum libero, turpis in, nullam arcu lobortis.\r\n","Photos":{"Original":"original\\KJ4091occasionals.jpg","Display":"display\\KJ4091occasionals.jpg","Mobile":"mobile\\KJ4091occasionals.jpg","Thumb":"thumb\\KJ4091occasionals.jpg"},"Price":649.0,"Categories":["Accent/Decor","Patio Table","Accent/Decor"]}