{"Id":4071,"Name":"KJexplorer918sofasetinscarlett","Slug":"KJexplorer918sofasetinscarlett","Description":"Nullam urna.\r\nMauris varius venenatis. Integer quis.\r\nProin ultricies vehicula, scelerisque sollicitudin.\r\n","Photos":{"Original":"KJexplorer918sofasetinscarlett.jpg","Display":"KJexplorer918sofasetinscarlett.jpg","Mobile":"KJexplorer918sofasetinscarlett.jpg","Thumb":"KJexplorer918sofasetinscarlett.jpg"},"Price":349.0,"Categories":["Living Room","Office","Living Room"],"Related":[{"Id":4071,"Name":"TMMISSION3672DOORBOOK","Slug":"TMMISSION3672DOORBOOK","Description":"Nullam urna.\r\nMauris varius venenatis. Integer quis.\r\nProin ultricies vehicula, scelerisque sollicitudin.\r\n","Photos":{"Original":"TMMISSION3672DOORBOOK.jpg","Display":"TMMISSION3672DOORBOOK.jpg","Mobile":"TMMISSION3672DOORBOOK.jpg","Thumb":"TMMISSION3672DOORBOOK.jpg"},"Price":149.0,"Categories":["Living Room","Office","Living Room"],"Related":[]},{"Id":4071,"Name":"1640bedroom-slf-monaco-inset-","Slug":"1640bedroom-slf-monaco-inset-","Description":"Nullam urna.\r\nMauris varius venenatis. Integer quis.\r\nProin ultricies vehicula, scelerisque sollicitudin.\r\n","Photos":{"Original":"1640bedroom-slf-monaco-inset-.jpg","Display":"1640bedroom-slf-monaco-inset-.jpg","Mobile":"1640bedroom-slf-monaco-inset-.jpg","Thumb":"1640bedroom-slf-monaco-inset-.jpg"},"Price":349.0,"Categories":["Living Room","Office","Living Room"],"Related":[]},{"Id":4071,"Name":"9880-X00-Titan-crib","Slug":"9880-X00-Titan-crib","Description":"Nullam urna.\r\nMauris varius venenatis. Integer quis.\r\nProin ultricies vehicula, scelerisque sollicitudin.\r\n","Photos":{"Original":"9880-X00-Titan-crib.jpg","Display":"9880-X00-Titan-crib.jpg","Mobile":"9880-X00-Titan-crib.jpg","Thumb":"9880-X00-Titan-crib.jpg"},"Price":149.0,"Categories":["Living Room","Office","Living Room"],"Related":[]}]}