{"Id":46521,"Name":"KJfairfax3130sectional","Description":"Dapibus ut phasellus. Eget purus reiciendis. Cras elit libero, lorem viverra, convallis leo. Nulla maecenas ipsum.\r\nVehicula vestibulum amet, litora massa, hendrerit ipsum. Commodo eget, sem tellus id, a sollicitudin eu. Lobortis eleifend, libero massa, praesent quisque ligula.\r\nNisl nunc, nisl justo, orci vel. Libero lobortis mollis, ac praesent placerat, in malesuada. Commodo nulla, elit dui.\r\nMi fermentum lectus, nec eros, nullam nunc cras. Viverra nam rutrum, velit dictum. Cras turpis quis. Amet risus, lacus dictumst.\r\n","Photos":{"Original":"original\\KJfairfax3130sectional.jpg","Display":"display\\KJfairfax3130sectional.jpg","Mobile":"mobile\\KJfairfax3130sectional.jpg","Thumb":"thumb\\KJfairfax3130sectional.jpg"},"Price":499.0,"Categories":["Foam Mattresses","Entertainment","Foam Mattresses"]}