{"Id":12214,"Name":"legacybritanniasideboard","Description":"Nunc vitae aliquam, nec gravida duis, nulla condimentum.\r\nAliquet id vitae, vitae ligula. Sociosqu vivamus integer. Vivamus lectus.\r\nUt wisi tristique, nec volutpat. Vel praesent, nec vel. Condimentum vel nam.\r\n","Photos":{"Original":"original\\legacybritanniasideboard.jpg","Display":"display\\legacybritanniasideboard.jpg","Mobile":"mobile\\legacybritanniasideboard.jpg","Thumb":"thumb\\legacybritanniasideboard.jpg"},"Price":299.0,"Categories":["Mattress","Accent/Decor","Mattress"]}