{"Id":46201,"Name":"MS2110palisadesPQBG","Description":"Sed sit quam, est semper eu. A arcu wisi. Vestibulum donec et, sollicitudin mi, euismod eleifend. Integer dicta. Urna leo class, in lectus, arcu nec tortor.\r\nLitora quis dui, integer vestibulum facilisi, nunc varius. Justo phasellus. Urna aliquet et. Sed nulla neque, nullam pede, in metus feugiat.\r\nTortor arcu, massa in, diam id. Massa pretium. Posuere ac sed, neque fringilla, ut vel sollicitudin. Per sodales, posuere urna, sollicitudin ut. Habitasse metus cras, sit ut vel.\r\nNon ac rutrum. Magna ac sed, adipiscing odio a, tempor mattis. Eget est eu, euismod vivamus.\r\n","Photos":{"Original":"original\\MS2110palisadesPQBG.jpg","Display":"display\\MS2110palisadesPQBG.jpg","Mobile":"mobile\\MS2110palisadesPQBG.jpg","Thumb":"thumb\\MS2110palisadesPQBG.jpg"},"Price":949.0,"Categories":["Youth - Bedroom Set","Living Room - Chairs","Youth - Bedroom Set"]}