{"Id":12913,"Name":"NCsoftie198recliningsofaset","Description":"Vitae enim wisi, felis sodales wisi.\r\nTellus arcu natoque, sagittis feugiat.\r\nUllamcorper eget erat. Vel at, lectus a feugiat. Porta dolor, nulla vel condimentum.\r\n","Photos":{"Original":"original\\NCsoftie198recliningsofaset.jpg","Display":"display\\NCsoftie198recliningsofaset.jpg","Mobile":"mobile\\NCsoftie198recliningsofaset.jpg","Thumb":"thumb\\NCsoftie198recliningsofaset.jpg"},"Price":299.0,"Categories":["Mattress","Dining","Mattress"]}