{"Id":24879,"Name":"NL-travelersretreat-010524931-GAT","Description":"Eget purus reiciendis. Ut nibh per, sed urna, quam autem tellus.\r\nPraesent sed sollicitudin, congue hac. Dignissim at. Sollicitudin est accumsan.\r\nSem lorem felis. Nec ipsum, ipsum tellus turpis.\r\n","Photos":{"Original":"original\\NL-travelersretreat-010524931-GAT.jpg","Display":"display\\NL-travelersretreat-010524931-GAT.jpg","Mobile":"mobile\\NL-travelersretreat-010524931-GAT.jpg","Thumb":"thumb\\NL-travelersretreat-010524931-GAT.jpg"},"Price":549.0,"Categories":["Youth","Office","Youth"]}