{"Id":11586,"Name":"NL-travelersretreat-010524980-CHR","Slug":"NL-travelersretreat-010524980-CHR","Description":"Accumsan wisi eu, sit ac, enim at rhoncus. Amet molestie dolor, ducimus id sagittis, tristique ratione.\r\nRhoncus quam parturient, sem sed. Nec mi, et porttitor. Non ratione elit.\r\nSed massa. Praesent pellentesque nulla, felis venenatis ut, diam vestibulum gravida. Lacus ut, elementum turpis.\r\n","Photos":{"Original":"NL-travelersretreat-010524980-CHR.jpg","Display":"NL-travelersretreat-010524980-CHR.jpg","Mobile":"NL-travelersretreat-010524980-CHR.jpg","Thumb":"NL-travelersretreat-010524980-CHR.jpg"},"Price":799.0,"Categories":["Mattress","Youth - Desks","Mattress"],"Related":[{"Id":11586,"Name":"GVcountyfair41463HFbunkbedgroup","Slug":"GVcountyfair41463HFbunkbedgroup","Photos":{"Original":"GVcountyfair41463HFbunkbedgroup.jpg","Display":"GVcountyfair41463HFbunkbedgroup.jpg","Mobile":"GVcountyfair41463HFbunkbedgroup.jpg","Thumb":"GVcountyfair41463HFbunkbedgroup.jpg"},"Price":299.0},{"Id":11586,"Name":"640-266-2pc-EngCOUNTRY","Slug":"640-266-2pc-EngCOUNTRY","Photos":{"Original":"640-266-2pc-EngCOUNTRY.jpg","Display":"640-266-2pc-EngCOUNTRY.jpg","Mobile":"640-266-2pc-EngCOUNTRY.jpg","Thumb":"640-266-2pc-EngCOUNTRY.jpg"},"Price":799.0},{"Id":11586,"Name":"rhythem-platfrom-bedroom","Slug":"rhythem-platfrom-bedroom","Photos":{"Original":"rhythem-platfrom-bedroom.jpg","Display":"rhythem-platfrom-bedroom.jpg","Mobile":"rhythem-platfrom-bedroom.jpg","Thumb":"rhythem-platfrom-bedroom.jpg"},"Price":299.0}],"Reviews":["Accumsan wisi eu, sit ac, enim at rhoncus. Amet molestie dolor, ducimus id sagittis, tristique ratione.\r\nRhoncus quam parturient, sem sed. Nec mi, et porttitor. Non ratione elit.\r\nSed massa. Praesent pellentesque nulla, felis venenatis ut, diam vestibulum gravida. Lacus ut, elementum turpis.\r\n"],"AvgRating":1}