{"Id":21301,"Name":"NMcalcutta31904ent","Description":"Luctus cursus, id eu at, dui est. Vivamus urna, ut elit, ipsum nunc sit. Vel curabitur, eu wisi.\r\nDuis sem, sed tincidunt, magna rhoncus. Nibh aliquam, facilisis nunc et, vestibulum nam.\r\nLobortis vitae. Curabitur laoreet, rutrum sed, ut lacus lorem. Tincidunt ligula vitae, velit adipiscing nonummy, et elit. Fringilla praesent, consectetuer id. Porttitor ut consectetuer, justo praesentium, odio wisi.\r\n","Photos":{"Original":"original\\NMcalcutta31904ent.jpg","Display":"display\\NMcalcutta31904ent.jpg","Mobile":"mobile\\NMcalcutta31904ent.jpg","Thumb":"thumb\\NMcalcutta31904ent.jpg"},"Price":949.0,"Categories":["Entertainment","Youth - Bedroom Set","Entertainment"]}