{"Id":42303,"Name":"NSromantikMATTRESS","Description":"Ullamcorper penatibus integer, augue congue justo. Eu quia in, facilisis velit volutpat. Accumsan diam. Ac et. Porttitor ut consectetuer, justo praesentium, odio wisi.\r\nEt leo wisi, vestibulum condimentum, ut massa sit. Et ad pellentesque, convallis turpis. Mollit in condimentum, ut lectus, suspendisse neque tellus. Egestas curabitur. Mauris fusce non, donec urna pellentesque.\r\nVitae netus et, proin eros in.\r\nNulla nulla qui. Lorem a nunc, quis eu, ut et. Tempor tortor. Nec lectus iaculis. Velit ut phasellus, eu diam, egestas eget.\r\n","Photos":{"Original":"original\\NSromantikMATTRESS.jpg","Display":"display\\NSromantikMATTRESS.jpg","Mobile":"mobile\\NSromantikMATTRESS.jpg","Thumb":"thumb\\NSromantikMATTRESS.jpg"},"Price":849.0,"Categories":["Youth - Accents","Patio Firepits","Youth - Accents"]}