{"Id":2867,"Name":"OAexcelsiorArmoire","Description":"Vestibulum in, integer arcu arcu.\r\nNon ornare integer, dignissim semper eget, nonummy mollit. Dolor consectetuer porta. Praesent sed sollicitudin, congue hac.\r\nUltrices nibh vel, magna cubilia id. Ut amet et. Luctus ut, nulla turpis. Mauris varius venenatis. Praesent lorem a, aptent donec.\r\n","Photos":{"Original":"original\\OAexcelsiorArmoire.jpg","Display":"display\\OAexcelsiorArmoire.jpg","Mobile":"mobile\\OAexcelsiorArmoire.jpg","Thumb":"thumb\\OAexcelsiorArmoire.jpg"},"Price":80.0,"Categories":["Living Room","Boxsprings","Living Room"]}