{"Id":30707,"Name":"palladio-sleigh-bedroom","Description":"Pharetra egestas, vel urna, pulvinar duis mauris. Sed quam viverra. Tortor sollicitudin, suscipit vivamus. Gravida imperdiet cras, erat amet, eget justo.\r\nSit turpis amet, lacus et. Fusce erat. Commodo eget, sem tellus id, a sollicitudin eu. Quis amet quam, et et placeat. Sollicitudin in consectetuer.\r\nQuam maecenas hymenaeos, luctus leo. Vestibulum in, integer arcu arcu. Dictum amet consectetuer. Felis non duis, volutpat fermentum.\r\nSapien morbi, dictum luctus luctus, hac purus quis. Odio malesuada lacinia, cras vestibulum, libero duis eleifend. Nullam turpis, lorem laoreet turpis, ex urna. Dolor commodo, sociosqu non, ligula nulla lacinia.\r\n","Photos":{"Original":"original\\palladio-sleigh-bedroom.jpg","Display":"display\\palladio-sleigh-bedroom.jpg","Mobile":"mobile\\palladio-sleigh-bedroom.jpg","Thumb":"thumb\\palladio-sleigh-bedroom.jpg"},"Price":649.0,"Categories":["Accent/Decor","Dining Room - Tables","Accent/Decor"]}