{"Id":26272,"Name":"PalmBeachDining","Description":"Ut lobortis, ac suspendisse, tristique arcu nibh. Nulla maecenas ipsum. Ut vehicula, pretium integer.\r\nIn vitae, at a at.\r\nPhasellus vestibulum. Vel congue a, habitasse tellus. Eget mi sem, erat nemo in, sit morbi interdum. Massa sed diam. Mi pede blandit, elit nullam nibh, arcu dapibus ut.\r\nSed ut a. Donec vestibulum, mauris placerat duis, erat molestie in. Eleifend at, et condimentum nunc.\r\n","Photos":{"Original":"original\\PalmBeachDining.jpg","Display":"display\\PalmBeachDining.jpg","Mobile":"mobile\\PalmBeachDining.jpg","Thumb":"thumb\\PalmBeachDining.jpg"},"Price":549.0,"Categories":["Youth","Dressers & Chests","Youth"]}