{"Id":19967,"Name":"pioneer1212.01","Description":"Lorem ut nulla, orci at. Tellus arcu natoque, sagittis feugiat.\r\nUt platea, nec sed, suscipit tincidunt. Mi a, taciti dui justo. Orci sint tempor, gravida mattis aliquam, ante sed. Ullamcorper eget erat.\r\nUllamcorper quis, velit suscipit. Fermentum turpis. Eu eget dignissim, lorem wisi suscipit, fusce nec suscipit. Nullam est dolor, mollis dignissim, leo vestibulum eget.\r\n","Photos":{"Original":"original\\pioneer1212.01.jpg","Display":"display\\pioneer1212.01.jpg","Mobile":"mobile\\pioneer1212.01.jpg","Thumb":"thumb\\pioneer1212.01.jpg"},"Price":449.0,"Categories":["Entertainment","Youth","Entertainment"]}