{"Id":30549,"Name":"plantationseating-southsea-benning","Description":"Sem lorem felis. Vivamus urna, ut elit, ipsum nunc sit. Donec quis. Duis commodo, sit libero nec.\r\nRidiculus convallis in, nam libero nulla. Porta dolor, nulla vel condimentum. Lectus vitae magna, placerat faucibus lorem. Elit blandit cursus, ad nullam.\r\nSit eleifend, odio integer. Non nisl in, metus proin. Tellus nulla. At nec, a lacinia laoreet. Mauris lacus a.\r\nEu quia in, facilisis velit volutpat. Molestie amet dictum, elit varius dapibus, et felis. Pellentesque lorem. Nec non. Mus viverra, elementum arcu in, mauris mattis.\r\n","Photos":{"Original":"original\\plantationseating-southsea-benning.jpg","Display":"display\\plantationseating-southsea-benning.jpg","Mobile":"mobile\\plantationseating-southsea-benning.jpg","Thumb":"thumb\\plantationseating-southsea-benning.jpg"},"Price":699.0,"Categories":["Accent/Decor","Youth - Storage","Accent/Decor"]}