{"Id":7849,"Name":"redone-heirloom-napoli","Slug":"redone-heirloom-napoli","Description":"Suscipit vivamus rutrum, sed et donec.\r\nSagittis fermentum, cras morbi nibh, a eu suspendisse. Enim ipsum mollis, adipiscing eros, in nunc.\r\nLectus sapien, porttitor donec fusce, et nascetur.\r\n","Photos":{"Original":"redone-heirloom-napoli.jpg","Display":"redone-heirloom-napoli.jpg","Mobile":"redone-heirloom-napoli.jpg","Thumb":"redone-heirloom-napoli.jpg"},"Price":299.0,"Categories":["Bedroom","Mattress","Bedroom"],"Related":[{"Id":7849,"Name":"97","Slug":"97","Photos":{"Original":"97.jpg","Display":"97.jpg","Mobile":"97.jpg","Thumb":"97.jpg"},"Price":199.0},{"Id":7849,"Name":"38","Slug":"38","Photos":{"Original":"38.jpg","Display":"38.jpg","Mobile":"38.jpg","Thumb":"38.jpg"},"Price":299.0},{"Id":7849,"Name":"7114-50p-primo-swann","Slug":"7114-50p-primo-swann","Photos":{"Original":"7114-50p-primo-swann.jpg","Display":"7114-50p-primo-swann.jpg","Mobile":"7114-50p-primo-swann.jpg","Thumb":"7114-50p-primo-swann.jpg"},"Price":199.0}],"Reviews":["Suscipit vivamus rutrum, sed et donec.\r\nSagittis fermentum, cras morbi nibh, a eu suspendisse. Enim ipsum mollis, adipiscing eros, in nunc.\r\nLectus sapien, porttitor donec fusce, et nascetur.\r\n"],"AvgRating":0}