{"Id":29748,"Name":"RIharmony28009rectangularENT","Description":"Ut convallis, posuere et, et dui. Ut pharetra, sem lorem vel, ullamcorper sapien felis. Mattis feugiat sodales, nulla vitae.\r\nPellentesque duis interdum, quia lectus, augue eros. Odio malesuada lacinia, cras vestibulum, libero duis eleifend. Ullamcorper eget erat. Suspendisse tincidunt.\r\nQuis sodales, maecenas blandit arcu. A aliquam nunc. A hendrerit. Odio malesuada lacinia, cras vestibulum, libero duis eleifend. Bibendum magna, sit lectus.\r\nVestibulum nec metus, a suspendisse. Augue suspendisse porta, maecenas ultrices scelerisque.\r\n","Photos":{"Original":"original\\RIharmony28009rectangularENT.jpg","Display":"display\\RIharmony28009rectangularENT.jpg","Mobile":"mobile\\RIharmony28009rectangularENT.jpg","Thumb":"thumb\\RIharmony28009rectangularENT.jpg"},"Price":649.0,"Categories":["Patio","Bases & Adjustable Bases","Patio"]}