{"Id":6721,"Name":"sofa-table","Description":"Tempus proin, sed mus, vestibulum tincidunt magna.\r\nVitae metus, elit urna ac, vestibulum vel. Mi donec in. Potenti interdum. Curae massa purus, justo rhoncus, tellus varius aliquet.\r\nNullam lacinia, eros diam pede, cras elementum sed. Velit mauris. Nullam non, consectetuer nunc ullamcorper, morbi suspendisse. Ullamcorper urna.\r\n","Photos":{"Original":"original\\sofa-table.jpg","Display":"display\\sofa-table.jpg","Mobile":"mobile\\sofa-table.jpg","Thumb":"thumb\\sofa-table.jpg"},"Price":199.0,"Categories":["Dining","Piers & Bookcases","Dining"]}