{"Id":35417,"Name":"ta-14700-prod-magnussen-oso","Description":"In tempor. Mi magna. Sed auctor.\r\nNibh consequat, id senectus auctor. Ac neque, at pellentesque vivamus. Tincidunt dictum orci.\r\nNibh tincidunt, dolor ut sollicitudin. Amet at est, sem vestibulum eu, mauris pellentesque sed.\r\nSed nulla neque, nullam pede, in metus feugiat. Maecenas est, id felis, placerat pellentesque suscipit.\r\n","Photos":{"Original":"original\\ta-14700-prod-magnussen-oso.jpg","Display":"display\\ta-14700-prod-magnussen-oso.jpg","Mobile":"mobile\\ta-14700-prod-magnussen-oso.jpg","Thumb":"thumb\\ta-14700-prod-magnussen-oso.jpg"},"Price":749.0,"Categories":["Hybrid Mattresses","Entertainment","Hybrid Mattresses"]}