{"Id":15759,"Name":"the8piecemetronightsdiningroom","Slug":"the8piecemetronightsdiningroom","Description":"Lobortis laoreet, dolor ante elementum.\r\nNam aliquam lorem. Leo integer, wisi dictum eu.\r\nDiam dapibus.\r\n","Photos":{"Original":"the8piecemetronightsdiningroom.jpg","Display":"the8piecemetronightsdiningroom.jpg","Mobile":"the8piecemetronightsdiningroom.jpg","Thumb":"the8piecemetronightsdiningroom.jpg"},"Price":349.0,"Categories":["Office","Entertainment","Office"],"Related":[{"Id":15759,"Name":"9190-930","Slug":"9190-930","Photos":{"Original":"9190-930.jpg","Display":"9190-930.jpg","Mobile":"9190-930.jpg","Thumb":"9190-930.jpg"},"Price":349.0},{"Id":15759,"Name":"816-200-rectangle-ARUBA","Slug":"816-200-rectangle-ARUBA","Photos":{"Original":"816-200-rectangle-ARUBA.jpg","Display":"816-200-rectangle-ARUBA.jpg","Mobile":"816-200-rectangle-ARUBA.jpg","Thumb":"816-200-rectangle-ARUBA.jpg"},"Price":349.0},{"Id":15759,"Name":"CrossRoadsQueenLPBed","Slug":"CrossRoadsQueenLPBed","Photos":{"Original":"CrossRoadsQueenLPBed.jpg","Display":"CrossRoadsQueenLPBed.jpg","Mobile":"CrossRoadsQueenLPBed.jpg","Thumb":"CrossRoadsQueenLPBed.jpg"},"Price":349.0}],"Reviews":["Lobortis laoreet, dolor ante elementum.\r\nNam aliquam lorem. Leo integer, wisi dictum eu.\r\nDiam dapibus.\r\n","Lobortis laoreet, dolor ante elementum.\r\nNam aliquam lorem. Leo integer, wisi dictum eu.\r\nDiam dapibus.\r\n"],"AvgRating":1}