{"Id":49790,"Name":"thehavanabayrounddining","Description":"Integer sed tempor. Lorem a nunc, quis eu, ut et. In turpis vitae, tortor maecenas dolor, vitae elementum consectetuer. Nullam urna. Lectus vitae magna, placerat faucibus lorem.\r\nInteger mattis donec. Ut donec, integer magna sodales.\r\nNibh mollis nonummy. Ipsum dolor, nunc fusce nec. Maecenas est, id felis, placerat pellentesque suscipit. Sed ut a. Gravida sunt vestibulum.\r\nEt duis, nunc turpis. Pellentesque lorem. Vehicula sociosqu suspendisse, integer praesent montes. Sociis vestibulum scelerisque, senectus pulvinar ornare. Tempus amet.\r\n","Photos":{"Original":"original\\thehavanabayrounddining.jpg","Display":"display\\thehavanabayrounddining.jpg","Mobile":"mobile\\thehavanabayrounddining.jpg","Thumb":"thumb\\thehavanabayrounddining.jpg"},"Price":999.0,"Categories":["Lounge Seating","Patio","Lounge Seating"]}