{"Id":18372,"Name":"theparkavenueposterbed","Description":"Dolor commodo, sociosqu non, ligula nulla lacinia. Nam aliquam lorem.\r\nAc neque, at pellentesque vivamus. Porta interdum, arcu phasellus. Vulputate nam, ligula magna id.\r\nCondimentum malesuada ultrices, aliquam nisl, quisque amet. Tincidunt in, dui egestas potenti, iaculis aptent nam. Cursus nam quam.\r\n","Photos":{"Original":"original\\theparkavenueposterbed.jpg","Display":"display\\theparkavenueposterbed.jpg","Mobile":"mobile\\theparkavenueposterbed.jpg","Thumb":"thumb\\theparkavenueposterbed.jpg"},"Price":699.0,"Categories":["Entertainment","Accent/Decor","Entertainment"]}