{"Id":2617,"Name":"TMOYSTER901-935ENTERCENT","Slug":"TMOYSTER901-935ENTERCENT","Description":"Donec duis ut.\r\nNon maecenas consequat, pede dictum sit, rutrum diam vitae. Sem lorem felis. Sit viverra, curabitur pretium integer, eu ullamcorper pellentesque. Nec scelerisque, eget vitae praesent.\r\nUrna semper risus, arcu vel, earum velit. Molestie arcu non, vitae ligula eget.\r\n","Photos":{"Original":"TMOYSTER901-935ENTERCENT.jpg","Display":"TMOYSTER901-935ENTERCENT.jpg","Mobile":"TMOYSTER901-935ENTERCENT.jpg","Thumb":"TMOYSTER901-935ENTERCENT.jpg"},"Price":849.0,"Categories":["Living Room","TV Consoles","Living Room"],"Related":[{"Id":2617,"Name":"8404-45-&-8404-48-&-8404-49-&-8404-97-old-tuscany","Slug":"8404-45-&-8404-48-&-8404-49-&-8404-97-old-tuscany","Photos":{"Original":"8404-45-&-8404-48-&-8404-49-&-8404-97-old-tuscany.jpg","Display":"8404-45-&-8404-48-&-8404-49-&-8404-97-old-tuscany.jpg","Mobile":"8404-45-&-8404-48-&-8404-49-&-8404-97-old-tuscany.jpg","Thumb":"8404-45-&-8404-48-&-8404-49-&-8404-97-old-tuscany.jpg"},"Price":80.0},{"Id":2617,"Name":"121758s","Slug":"121758s","Photos":{"Original":"121758s.jpg","Display":"121758s.jpg","Mobile":"121758s.jpg","Thumb":"121758s.jpg"},"Price":849.0},{"Id":2617,"Name":"RPcallahan-configB-slpersect","Slug":"RPcallahan-configB-slpersect","Photos":{"Original":"RPcallahan-configB-slpersect.jpg","Display":"RPcallahan-configB-slpersect.jpg","Mobile":"RPcallahan-configB-slpersect.jpg","Thumb":"RPcallahan-configB-slpersect.jpg"},"Price":80.0}],"Reviews":[],"AvgRating":0}