{"Id":4022,"Name":"tvcabinet1235W","Slug":"tvcabinet1235W","Description":"Sem consectetuer, erat urna lectus.\r\nEros enim quam, conubia libero.\r\nPurus ligula sem, proin metus velit.\r\n","Photos":{"Original":"tvcabinet1235W.jpg","Display":"tvcabinet1235W.jpg","Mobile":"tvcabinet1235W.jpg","Thumb":"tvcabinet1235W.jpg"},"Price":949.0,"Categories":["Living Room","Living Room - Chairs","Living Room"],"Related":[{"Id":4022,"Name":"161-2","Slug":"161-2","Description":"Sem consectetuer, erat urna lectus.\r\nEros enim quam, conubia libero.\r\nPurus ligula sem, proin metus velit.\r\n","Photos":{"Original":"161-2.jpg","Display":"161-2.jpg","Mobile":"161-2.jpg","Thumb":"161-2.jpg"},"Price":149.0,"Categories":["Living Room","Living Room - Chairs","Living Room"],"Related":[]},{"Id":4022,"Name":"tra","Slug":"tra","Description":"Sem consectetuer, erat urna lectus.\r\nEros enim quam, conubia libero.\r\nPurus ligula sem, proin metus velit.\r\n","Photos":{"Original":"tra.jpg","Display":"tra.jpg","Mobile":"tra.jpg","Thumb":"tra.jpg"},"Price":949.0,"Categories":["Living Room","Living Room - Chairs","Living Room"],"Related":[]},{"Id":4022,"Name":"2-piece-Camden-occasionals","Slug":"2-piece-Camden-occasionals","Description":"Sem consectetuer, erat urna lectus.\r\nEros enim quam, conubia libero.\r\nPurus ligula sem, proin metus velit.\r\n","Photos":{"Original":"2-piece-Camden-occasionals.jpg","Display":"2-piece-Camden-occasionals.jpg","Mobile":"2-piece-Camden-occasionals.jpg","Thumb":"2-piece-Camden-occasionals.jpg"},"Price":149.0,"Categories":["Living Room","Living Room - Chairs","Living Room"],"Related":[]}]}