{"Id":19603,"Name":"untitled2","Description":"Rhoncus quam parturient, sem sed. Eget dapibus cursus.\r\nMassa sed diam. Elementum feugiat velit, dictum libero. Duis faucibus, molestie ante adipiscing, id eget elit.\r\nTortor sollicitudin, suscipit vivamus. Tellus eleifend, ut semper, pellentesque diam. Mauris donec sed. Dui dis metus. In vitae, at a at.\r\n","Photos":{"Original":"original\\untitled2.jpg","Display":"display\\untitled2.jpg","Mobile":"mobile\\untitled2.jpg","Thumb":"thumb\\untitled2.jpg"},"Price":449.0,"Categories":["Entertainment","Nightstands","Entertainment"]}