{"Id":1007,"Name":"W8234bed-Good-Wakefield","Description":"Urna tempus luctus, sed pharetra.\r\nNunc vitae aliquam, nec gravida duis, nulla condimentum. Nibh aliquam, facilisis nunc et, vestibulum nam. Elementum a accumsan.\r\nUt sed, integer nec, quam quam. A autem sed.\r\n","Photos":{"Original":"original\\W8234bed-Good-Wakefield.jpg","Display":"display\\W8234bed-Good-Wakefield.jpg","Mobile":"mobile\\W8234bed-Good-Wakefield.jpg","Thumb":"thumb\\W8234bed-Good-Wakefield.jpg"},"Price":349.0,"Categories":["Living Room","Office","Living Room"]}