{"Id":11427,"Name":"woodridgevanitybedroom","Description":"Lorem ipsum dolor sit amet, ornare neque vehicula, sapien donec nunc, nisl sagittis.\r\nUllamcorper quis, velit suscipit. Libero sit, vestibulum porta, non sed tellus.\r\nSem ipsum ac, tortor augue lobortis, viverra id. Sit volutpat necessitatibus, suspendisse mauris, convallis mauris sapien. Interdum ante.\r\n","Photos":{"Original":"original\\woodridgevanitybedroom.jpg","Display":"display\\woodridgevanitybedroom.jpg","Mobile":"mobile\\woodridgevanitybedroom.jpg","Thumb":"thumb\\woodridgevanitybedroom.jpg"},"Price":49.0,"Categories":["Mattress","Living Room","Mattress"]}