{"Id":24574,"Name":"YLsouthport440honeypinecasualdining","Description":"Tincidunt in, dui egestas potenti, iaculis aptent nam. Ipsum dolor, nunc fusce nec. Mattis feugiat sodales, nulla vitae.\r\nVelit arcu, vestibulum feugiat faucibus, libero pretium phasellus. Sed wisi consectetuer, urna natoque justo. Lobortis vitae. Suscipit volutpat, wisi elit. Lobortis eleifend, libero massa, praesent quisque ligula.\r\nNec massa nec, porttitor amet volutpat. Vel congue a, habitasse tellus. Magna consectetuer, consectetuer metus erat. Nisl gravida faucibus, in tortor donec, pede porta amet.\r\n","Photos":{"Original":"original\\YLsouthport440honeypinecasualdining.jpg","Display":"display\\YLsouthport440honeypinecasualdining.jpg","Mobile":"mobile\\YLsouthport440honeypinecasualdining.jpg","Thumb":"thumb\\YLsouthport440honeypinecasualdining.jpg"},"Price":549.0,"Categories":["Youth","Piers & Bookcases","Youth"]}