{"Id":18431,"Name":"YTbalmoral9461drawercocktail","Description":"Tempor nulla libero, est vivamus, turpis non. Sed auctor.\r\nUt platea, nec sed, suscipit tincidunt. Duis faucibus, molestie ante adipiscing, id eget elit. Sociis eu. Felis porttitor, sodales per.\r\nPharetra egestas, vel urna, pulvinar duis mauris. Accumsan diam.\r\n","Photos":{"Original":"original\\YTbalmoral9461drawercocktail.jpg","Display":"display\\YTbalmoral9461drawercocktail.jpg","Mobile":"mobile\\YTbalmoral9461drawercocktail.jpg","Thumb":"thumb\\YTbalmoral9461drawercocktail.jpg"},"Price":399.0,"Categories":["Entertainment","Fireplaces","Entertainment"]}